MAIA/__init__.py
MAIA/_version.py
MAIA/dashboard_utils.py
MAIA/helm_values.py
MAIA/keycloak_utils.py
MAIA/kubernetes_utils.py
MAIA/maia_admin.py
MAIA/maia_core.py
MAIA/maia_docker_images.py
MAIA/maia_fn.py
MAIA/versions.py
MAIA/configs/MAIA_realm_template.json
MAIA/configs/docker_versions.yaml
MAIA_scripts/MAIA_Install.py
MAIA_scripts/MAIA_build_images.py
MAIA_scripts/MAIA_change_keycloak_client_secret.py
MAIA_scripts/MAIA_configure_keycloak.py
MAIA_scripts/MAIA_create_JupyterHub_config.py
MAIA_scripts/MAIA_deploy_helm_chart.py
MAIA_scripts/MAIA_install_admin_toolkit.py
MAIA_scripts/MAIA_install_core_toolkit.py
MAIA_scripts/MAIA_install_project_toolkit.py
MAIA_scripts/MAIA_send_all_user_email.py
MAIA_scripts/MAIA_send_welcome_user_mail.py
MAIA_scripts/__init__.py
maia_toolkit-2.4.4.data/data/requirements.txt
maia_toolkit-2.4.4.data/scripts/MAIA_Configure_Installation.sh
maia_toolkit-2.4.4.dist-info/licenses/LICENSE
maia_toolkit-2.4.4.dist-info/METADATA
maia_toolkit-2.4.4.dist-info/WHEEL
maia_toolkit-2.4.4.dist-info/entry_points.txt
maia_toolkit-2.4.4.dist-info/top_level.txt
maia_toolkit-2.4.4.dist-info/RECORD
