Metadata-Version: 2.4
Name: maia-toolkit
Version: 2.4.4
Summary: MAIA is a Kubernetes-based collaborative platform for Medical AI, with integration in the clinical workflow of AI.
Home-page: https://github.com/minnelab/MAIA.git
Author: Bendazzoli Simone
Author-email: simben@kth.se
License: GPLv3
Project-URL: Documentation, https://maia-toolkit.readthedocs.io
Project-URL: Bug Tracker, https://github.com/minnelab/MAIA
Project-URL: Source Code, https://github.com/minnelab/MAIA/issues
Keywords: helm,kubernetes,maia,resource deployment
Platform: OS Independent
Requires-Python: >=3.8
License-File: LICENSE
Requires-Dist: ruamel_yaml
Requires-Dist: python-keycloak
Requires-Dist: kubernetes
Requires-Dist: minio
Requires-Dist: numpy
Requires-Dist: omegaconf
Requires-Dist: pandas
Requires-Dist: pyhelm3
Requires-Dist: PyYAML
Requires-Dist: Requests
Requires-Dist: SQLAlchemy
Requires-Dist: toml
Requires-Dist: nltk
Requires-Dist: click
Requires-Dist: hydra-core
Requires-Dist: python-on-whales
Requires-Dist: rich
Requires-Dist: loguru
Requires-Dist: ansible
Requires-Dist: dotenv
Dynamic: keywords
Dynamic: license-file
